cqTools/__init__.py
cqTools/StudentSearch/__init__.py
cqTools/StudentSearch/utils/__init__.py
cqTools/StudentSearch/utils/login.py
cqTools-0.0.7.dist-info/LICENSE
cqTools-0.0.7.dist-info/METADATA
cqTools-0.0.7.dist-info/WHEEL
cqTools-0.0.7.dist-info/top_level.txt
cqTools-0.0.7.dist-info/RECORD
