Metadata-Version: 2.1
Name: cqTools
Version: 0.0.7
Summary: A example package.
Home-page: https://github.com/cq128
Author: 陈乾
Author-email: 3206293873@qq.com
License: UNKNOWN
Platform: UNKNOWN
Classifier: Programming Language :: Python :: 3
Classifier: License :: OSI Approved :: MIT License
Classifier: Operating System :: OS Independent
License-File: LICENSE
